volatility3/__init__.py
volatility3/cli/__init__.py
volatility3/cli/text_filter.py
volatility3/cli/text_renderer.py
volatility3/cli/volargparse.py
volatility3/cli/volshell/__init__.py
volatility3/cli/volshell/generic.py
volatility3/cli/volshell/linux.py
volatility3/cli/volshell/mac.py
volatility3/cli/volshell/windows.py
volatility3/framework/__init__.py
volatility3/framework/deprecation.py
volatility3/framework/exceptions.py
volatility3/framework/versionutils.py
volatility3/framework/automagic/__init__.py
volatility3/framework/automagic/construct_layers.py
volatility3/framework/automagic/linux.py
volatility3/framework/automagic/mac.py
volatility3/framework/automagic/module.py
volatility3/framework/automagic/pdbscan.py
volatility3/framework/automagic/stacker.py
volatility3/framework/automagic/symbol_cache.py
volatility3/framework/automagic/symbol_finder.py
volatility3/framework/automagic/windows.py
volatility3/framework/configuration/__init__.py
volatility3/framework/configuration/requirements.py
volatility3/framework/constants/__init__.py
volatility3/framework/constants/_version.py
volatility3/framework/constants/architectures.py
volatility3/framework/constants/linux/__init__.py
volatility3/framework/constants/windows/__init__.py
volatility3/framework/contexts/__init__.py
volatility3/framework/interfaces/__init__.py
volatility3/framework/interfaces/automagic.py
volatility3/framework/interfaces/configuration.py
volatility3/framework/interfaces/context.py
volatility3/framework/interfaces/layers.py
volatility3/framework/interfaces/objects.py
volatility3/framework/interfaces/plugins.py
volatility3/framework/interfaces/renderers.py
volatility3/framework/interfaces/symbols.py
volatility3/framework/layers/__init__.py
volatility3/framework/layers/avml.py
volatility3/framework/layers/cloudstorage.py
volatility3/framework/layers/crash.py
volatility3/framework/layers/elf.py
volatility3/framework/layers/intel.py
volatility3/framework/layers/leechcore.py
volatility3-2.27.0.dist-info/LICENSE.txt
volatility3-2.27.0.dist-info/METADATA
volatility3-2.27.0.dist-info/WHEEL
volatility3-2.27.0.dist-info/entry_points.txt
volatility3-2.27.0.dist-info/top_level.txt
volatility3-2.27.0.dist-info/RECORD
