Metadata-Version: 2.1
Name: volatility3
Version: 2.27.0
Summary: Memory forensics framework
Author-email: Volatility Foundation <volatility@volatilityfoundation.org>
License: VSL
Project-URL: homepage, https://github.com/volatilityfoundation/volatility3/
Project-URL: documentation, https://volatility3.readthedocs.io/
Project-URL: repository, https://github.com/volatilityfoundation/volatility3
Project-URL: issues, https://github.com/volatilityfoundation/volatility3/issues
Keywords: volatility,memory,forensics,framework,windows,linux,volshell
Requires-Python: >=3.8.0
License-File: LICENSE.txt
Requires-Dist: pefile>=2024.8.26
Provides-Extra: full
Requires-Dist: yara-python<5,>=4.5.1; extra == "full"
Requires-Dist: capstone<6,>=5.0.3; extra == "full"
Requires-Dist: pycryptodome<4,>=3.21.0; extra == "full"
Requires-Dist: leechcorepyc<3,>=2.19.2; sys_platform != "darwin" and extra == "full"
Requires-Dist: pillow<11.0.0,>=10.0.0; extra == "full"
Provides-Extra: cloud
Requires-Dist: gcsfs>=2024.10.0; extra == "cloud"
Requires-Dist: s3fs>=2024.10.0; extra == "cloud"
Provides-Extra: dev
Requires-Dist: volatility3[cloud,full]; extra == "dev"
Requires-Dist: jsonschema<5,>=4.23.0; extra == "dev"
Requires-Dist: pyinstaller<7,>=6.5.0; extra == "dev"
Requires-Dist: pyinstaller-hooks-contrib>=2024.9; extra == "dev"
Requires-Dist: types-jsonschema<5,>=4.23.0; extra == "dev"
Provides-Extra: arrow
Requires-Dist: pyarrow>=17.0.0; extra == "arrow"
Provides-Extra: test
Requires-Dist: volatility3[dev]; extra == "test"
Requires-Dist: pytest<9,>=8.3.3; extra == "test"
Requires-Dist: pytest-cov<7,>=5; extra == "test"
Requires-Dist: yara-x<1,>=0.10.0; extra == "test"
Provides-Extra: docs
Requires-Dist: volatility3[dev]; extra == "docs"
Requires-Dist: sphinx<9,>=4.0.0; extra == "docs"
Requires-Dist: sphinx-autodoc-typehints<4,>=3.0.0; python_version >= "3.11" and extra == "docs"
Requires-Dist: sphinx-rtd-theme<4,>=3.0.1; extra == "docs"
